{
  "schema_version": 1,
  "language": "Korean",
  "id": "ko_past",
  "title": "Tiempo pasado",
  "description": "Hablar de acciones y estados pasados.",
  "patterns": [
    "-았/었어요",
    "했어요"
  ],
  "items": [
    {
      "book_code": "HS-B02",
      "book_title": "Libro 2: Un Nuevo Hogar",
      "track_id": "2055",
      "lesson": 24,
      "sequence": 1,
      "speaker": "Joon",
      "text": "처음 보는 얼굴이네요. 어디에서 왔어요?",
      "translation": "Es una cara que veo por primera vez. ¿De dónde vienes?",
      "audio_path": "books/HS-B02/audio/L24-01 - 2055 - Joon - 처음 보는 얼굴이네요. 어디에서 왔어요.mp3",
      "pattern": "어디",
      "difficulty": "A1",
      "explanation_ref": "2055",
      "has_explanation": true
    },
    {
      "book_code": "HS-B02",
      "book_title": "Libro 2: Un Nuevo Hogar",
      "track_id": "2064",
      "lesson": 25,
      "sequence": 4,
      "speaker": "Joon",
      "text": "처음이면 제가 같이 갈게요. 가격을 물어보는 법을 알려 줄게요.",
      "translation": "Si es tu primera vez, iré contigo. Te enseñaré cómo preguntar precios.",
      "audio_path": "books/HS-B02/audio/L25-04 - 2064 - Joon - 처음이면 제가 같이 갈게요. 가격을 물어보는 법을 알려 줄게요.mp3",
      "pattern": "",
      "difficulty": "A1",
      "explanation_ref": "2064",
      "has_explanation": true
    },
    {
      "book_code": "HS-B02",
      "book_title": "Libro 2: Un Nuevo Hogar",
      "track_id": "2071",
      "lesson": 26,
      "sequence": 5,
      "speaker": "Joon",
      "text": "잘했어요. 이제 다른 물건도 물어보세요.",
      "translation": "Lo hiciste bien. Ahora pregunta por otra cosa también.",
      "audio_path": "books/HS-B02/audio/L26-05 - 2071 - Joon - 잘했어요. 이제 다른 물건도 물어보세요.mp3",
      "pattern": "했어요",
      "difficulty": "A1",
      "explanation_ref": "2071",
      "has_explanation": true
    },
    {
      "book_code": "HS-B02",
      "book_title": "Libro 2: Un Nuevo Hogar",
      "track_id": "2081",
      "lesson": 28,
      "sequence": 3,
      "speaker": "Aru",
      "text": "처음 만났을 때보다 훨씬 많이 말할 수 있어요.",
      "translation": "Puedes hablar muchísimo más que cuando nos conocimos por primera vez.",
      "audio_path": "books/HS-B02/audio/L28-03 - 2081 - Aru - 처음 만났을 때보다 훨씬 많이 말할 수 있어요.mp3",
      "pattern": "있어요",
      "difficulty": "A1",
      "explanation_ref": "2081",
      "has_explanation": true
    },
    {
      "book_code": "HS-B03",
      "book_title": "Libro 3- Más allá de la aldea",
      "track_id": "3003",
      "lesson": 29,
      "sequence": 3,
      "speaker": "Aru",
      "text": "네. 이곳 밖에도 여러 마을이 있어요.",
      "translation": "Sí. Fuera de aquí también hay varias aldeas.",
      "audio_path": "books/HS-B03/audio/L29-03 - 3003 - Aru - 네. 이곳 밖에도 여러 마을이 있어요.mp3",
      "pattern": "있어요",
      "difficulty": "A1",
      "explanation_ref": "3003",
      "has_explanation": true
    },
    {
      "book_code": "HS-B03",
      "book_title": "Libro 3- Más allá de la aldea",
      "track_id": "3029",
      "lesson": 33,
      "sequence": 5,
      "speaker": "Joon",
      "text": "대신 천천히 걸어야 해요. 우리도 처음 가는 길이에요.",
      "translation": "Pero tenemos que caminar despacio. Nosotros también vamos por primera vez.",
      "audio_path": "books/HS-B03/audio/L33-05 - 3029 - Joon - 대신 천천히 걸어야 해요. 우리도 처음 가는 길이에요.mp3",
      "pattern": "",
      "difficulty": "A1",
      "explanation_ref": "3029",
      "has_explanation": true
    },
    {
      "book_code": "HS-B03",
      "book_title": "Libro 3- Más allá de la aldea",
      "track_id": "3040",
      "lesson": 35,
      "sequence": 4,
      "speaker": "Aru",
      "text": "저도 그렇게 생각해요. 처음에는 믿기 어려웠어요.",
      "translation": "Yo también pienso eso. Al principio era difícil de creer.",
      "audio_path": "books/HS-B03/audio/L35-04 - 3040 - Aru - 저도 그렇게 생각해요. 처음에는 믿기 어려웠어요.mp3",
      "pattern": "",
      "difficulty": "A1",
      "explanation_ref": "3040",
      "has_explanation": true
    },
    {
      "book_code": "HS-B03",
      "book_title": "Libro 3- Más allá de la aldea",
      "track_id": "3043",
      "lesson": 36,
      "sequence": 1,
      "speaker": "Aru",
      "text": "비가 오기 시작했어요. 빨리 나무 아래로 가요.",
      "translation": "Empezó a llover. Vamos rápido debajo de los árboles.",
      "audio_path": "books/HS-B03/audio/L36-01 - 3043 - Aru - 비가 오기 시작했어요. 빨리 나무 아래로 가요.mp3",
      "pattern": "했어요",
      "difficulty": "A1",
      "explanation_ref": "3043",
      "has_explanation": true
    },
    {
      "book_code": "HS-B03",
      "book_title": "Libro 3- Más allá de la aldea",
      "track_id": "3064",
      "lesson": 39,
      "sequence": 4,
      "speaker": "Joon",
      "text": "괜찮은 가격이에요. 여행할 때는 가벼운 음식이 중요해요.",
      "translation": "Es buen precio. Cuando viajas, la comida ligera es importante.",
      "audio_path": "books/HS-B03/audio/L39-04 - 3064 - Joon - 괜찮은 가격이에요. 여행할 때는 가벼운 음식이 중요해요.mp3",
      "pattern": "",
      "difficulty": "A1",
      "explanation_ref": "3064",
      "has_explanation": true
    },
    {
      "book_code": "HS-B04",
      "book_title": "Libro 4 — La Ciudad",
      "track_id": "4009",
      "lesson": 44,
      "sequence": 3,
      "speaker": "Dueña",
      "text": "큰 방은 하나 남았어요. 하지만 조금 비싸요.",
      "translation": "Queda una habitación grande. Pero es un poco cara.",
      "audio_path": "books/HS-B04/audio/L44-03 - 4009 - Dueña - 큰 방은 하나 남았어요. 하지만 조금 비싸요.mp3",
      "pattern": "-지만",
      "difficulty": "A1",
      "explanation_ref": "4009",
      "has_explanation": true
    },
    {
      "book_code": "HS-B04",
      "book_title": "Libro 4 — La Ciudad",
      "track_id": "4035",
      "lesson": 48,
      "sequence": 5,
      "speaker": "Comerciante",
      "text": "물론이죠. 시작하기 전에 가격을 정해요.",
      "translation": "Claro. Antes de empezar, fijemos el precio.",
      "audio_path": "books/HS-B04/audio/L48-05 - 4035 - Comerciante - 물론이죠. 시작하기 전에 가격을 정해요.mp3",
      "pattern": "",
      "difficulty": "A1",
      "explanation_ref": "4035",
      "has_explanation": true
    },
    {
      "book_code": "HS-B04",
      "book_title": "Libro 4 — La Ciudad",
      "track_id": "4056",
      "lesson": 52,
      "sequence": 2,
      "speaker": "Aru",
      "text": "전에 이런 곳에 와 본 적이 있어요?",
      "translation": "¿Has venido antes a un lugar como este?",
      "audio_path": "books/HS-B04/audio/L52-02 - 4056 - Aru - 전에 이런 곳에 와 본 적이 있어요.mp3",
      "pattern": "있어요",
      "difficulty": "A1",
      "explanation_ref": "4056",
      "has_explanation": true
    },
    {
      "book_code": "HS-B04",
      "book_title": "Libro 4 — La Ciudad",
      "track_id": "4070",
      "lesson": 54,
      "sequence": 4,
      "speaker": "Joon",
      "text": "네. 문도 닫았고 창문도 확인했어요.",
      "translation": "Sí. Cerré la puerta y también revisé la ventana.",
      "audio_path": "books/HS-B04/audio/L54-04 - 4070 - Joon - 네. 문도 닫았고 창문도 확인했어요.mp3",
      "pattern": "했어요",
      "difficulty": "A1",
      "explanation_ref": "4070",
      "has_explanation": true
    },
    {
      "book_code": "HS-B04",
      "book_title": "Libro 4 — La Ciudad",
      "track_id": "4082",
      "lesson": 56,
      "sequence": 4,
      "speaker": "Joon",
      "text": "도시 밖의 길은 더 어려울 거예요.",
      "translation": "El camino fuera de la ciudad será más difícil.",
      "audio_path": "books/HS-B04/audio/L56-04 - 4082 - Joon - 도시 밖의 길은 더 어려울 거예요.mp3",
      "pattern": "",
      "difficulty": "A1",
      "explanation_ref": "4082",
      "has_explanation": true
    },
    {
      "book_code": "HS-VARIETY-S01E01",
      "book_title": "수상한 하루 — Episodio 1: El Invitado Sospechoso",
      "track_id": "V5008",
      "lesson": 1,
      "sequence": 8,
      "speaker": "Bora",
      "text": "봐요! 벌써 위치를 확인했어요. 뭔가 계획이 있는 거예요.",
      "translation": "¡Vieron! Ya revisó la posición. Tiene algún plan.",
      "audio_path": "books/HS-VARIETY-S01E01/audio/L01-08 - V5008 - Bora - 봐요! 벌써 위치를 확인했어요. 뭔가 계획이 있는 거예요.mp3",
      "pattern": "했어요",
      "difficulty": "A1",
      "explanation_ref": "V5008",
      "has_explanation": true
    },
    {
      "book_code": "HS-VARIETY-S01E01",
      "book_title": "수상한 하루 — Episodio 1: El Invitado Sospechoso",
      "track_id": "V5021",
      "lesson": 2,
      "sequence": 6,
      "speaker": "Dami",
      "text": "언니, 너무 빠르잖아요. 아직 자기소개도 끝나지 않았어요.",
      "translation": "Bora, vas demasiado rápido. Ni siquiera terminó su presentación.",
      "audio_path": "books/HS-VARIETY-S01E01/audio/L02-06 - V5021 - Dami - 언니, 너무 빠르잖아요. 아직 자기소개도 끝나지 않았어요.mp3",
      "pattern": "",
      "difficulty": "A1",
      "explanation_ref": "V5021",
      "has_explanation": true
    },
    {
      "book_code": "HS-VARIETY-S01E01",
      "book_title": "수상한 하루 — Episodio 1: El Invitado Sospechoso",
      "track_id": "V5024",
      "lesson": 2,
      "sequence": 9,
      "speaker": "Minho",
      "text": "배우러 왔다고 했지만, 우리 프로그램은 배우기 전에 살아남아야 합니다.",
      "translation": "Dice que vino a aprender, pero en nuestro programa hay que sobrevivir antes de aprender.",
      "audio_path": "books/HS-VARIETY-S01E01/audio/L02-09 - V5024 - Minho - 배우러 왔다고 했지만, 우리 프로그램은 배우기 전에 살아남아야 합니다.mp3",
      "pattern": "-지만",
      "difficulty": "A1",
      "explanation_ref": "V5024",
      "has_explanation": true
    },
    {
      "book_code": "HS-VARIETY-S01E01",
      "book_title": "수상한 하루 — Episodio 1: El Invitado Sospechoso",
      "track_id": "V5025",
      "lesson": 2,
      "sequence": 10,
      "speaker": "Kang PD",
      "text": "자기소개가 끝나면 바로 첫 번째 테스트를 시작하겠습니다.",
      "translation": "Cuando terminen las presentaciones, empezaremos inmediatamente la primera prueba.",
      "audio_path": "books/HS-VARIETY-S01E01/audio/L02-10 - V5025 - Kang PD - 자기소개가 끝나면 바로 첫 번째 테스트를 시작하겠습니다.mp3",
      "pattern": "",
      "difficulty": "A1",
      "explanation_ref": "V5025",
      "has_explanation": true
    },
    {
      "book_code": "HS-VARIETY-S01E01",
      "book_title": "수상한 하루 — Episodio 1: El Invitado Sospechoso",
      "track_id": "V5027",
      "lesson": 2,
      "sequence": 12,
      "speaker": "Taeyun",
      "text": "그 표정 봤어요? 진짜 처음 듣는 사람 표정이 아니에요.",
      "translation": "¿Vieron esa cara? No es la cara de alguien que lo escucha por primera vez.",
      "audio_path": "books/HS-VARIETY-S01E01/audio/L02-12 - V5027 - Taeyun - 그 표정 봤어요 진짜 처음 듣는 사람 표정이 아니에요.mp3",
      "pattern": "",
      "difficulty": "A1",
      "explanation_ref": "V5027",
      "has_explanation": true
    },
    {
      "book_code": "HS-VARIETY-S01E01",
      "book_title": "수상한 하루 — Episodio 1: El Invitado Sospechoso",
      "track_id": "V5029",
      "lesson": 2,
      "sequence": 14,
      "speaker": "Bora",
      "text": "진짜라는 말을 너무 빨리 했어요. 더 수상해졌어요.",
      "translation": "Dijo “de verdad” demasiado rápido. Se volvió más sospechoso.",
      "audio_path": "books/HS-VARIETY-S01E01/audio/L02-14 - V5029 - Bora - 진짜라는 말을 너무 빨리 했어요. 더 수상해졌어요.mp3",
      "pattern": "했어요",
      "difficulty": "A1",
      "explanation_ref": "V5029",
      "has_explanation": true
    },
    {
      "book_code": "HS-VARIETY-S01E01",
      "book_title": "수상한 하루 — Episodio 1: El Invitado Sospechoso",
      "track_id": "V5031",
      "lesson": 3,
      "sequence": 1,
      "speaker": "Kang PD",
      "text": "첫 번째 미션은 금지어 게임입니다. 각자 말하면 안 되는 단어가 하나씩 있습니다.",
      "translation": "La primera misión es el juego de palabras prohibidas. Cada uno tiene una palabra que no debe decir.",
      "audio_path": "books/HS-VARIETY-S01E01/audio/L03-01 - V5031 - Kang PD - 첫 번째 미션은 금지어 게임입니다. 각자 말하면 안 되는 단어가 하나씩 있습니다.mp3",
      "pattern": "",
      "difficulty": "A1",
      "explanation_ref": "V5031",
      "has_explanation": true
    },
    {
      "book_code": "HS-VARIETY-S01E01",
      "book_title": "수상한 하루 — Episodio 1: El Invitado Sospechoso",
      "track_id": "V5037",
      "lesson": 3,
      "sequence": 7,
      "speaker": "Taeyun",
      "text": "아니, 왜 시작도 전에 저를 막아요?",
      "translation": "Oye, ¿por qué me bloquean antes de empezar?",
      "audio_path": "books/HS-VARIETY-S01E01/audio/L03-07 - V5037 - Taeyun - 아니, 왜 시작도 전에 저를 막아요.mp3",
      "pattern": "",
      "difficulty": "A1",
      "explanation_ref": "V5037",
      "has_explanation": true
    },
    {
      "book_code": "HS-VARIETY-S01E01",
      "book_title": "수상한 하루 — Episodio 1: El Invitado Sospechoso",
      "track_id": "V5048",
      "lesson": 4,
      "sequence": 3,
      "speaker": "Bora",
      "text": "오, 재미있다고 했어요. 혹시 그게 금지어였으면 바로 끝났겠네요.",
      "translation": "Oh, dijo divertido. Si esa fuera la palabra prohibida, ya habría terminado.",
      "audio_path": "books/HS-VARIETY-S01E01/audio/L04-03 - V5048 - Bora - 오, 재미있다고 했어요. 혹시 그게 금지어였으면 바로 끝났겠네요.mp3",
      "pattern": "했어요",
      "difficulty": "A1",
      "explanation_ref": "V5048",
      "has_explanation": true
    },
    {
      "book_code": "HS-VARIETY-S01E01",
      "book_title": "수상한 하루 — Episodio 1: El Invitado Sospechoso",
      "track_id": "V5052",
      "lesson": 4,
      "sequence": 7,
      "speaker": "Taeyun",
      "text": "봤죠? 방금 뭔가 피했어요! 저건 습관이 있는 사람의 움직임이에요.",
      "translation": "¿Lo vieron? ¡Acaba de evitar algo! Ese es el movimiento de alguien con un hábito.",
      "audio_path": "books/HS-VARIETY-S01E01/audio/L04-07 - V5052 - Taeyun - 봤죠 방금 뭔가 피했어요! 저건 습관이 있는 사람의 움직임이에요.mp3",
      "pattern": "했어요",
      "difficulty": "A1",
      "explanation_ref": "V5052",
      "has_explanation": true
    },
    {
      "book_code": "HS-VARIETY-S01E01",
      "book_title": "수상한 하루 — Episodio 1: El Invitado Sospechoso",
      "track_id": "V5091",
      "lesson": 6,
      "sequence": 15,
      "speaker": "Kang PD",
      "text": "주문 성공입니다. 파란 팀은 첫 번째 힌트를 받습니다.",
      "translation": "Orden exitosa. El equipo azul recibe la primera pista.",
      "audio_path": "books/HS-VARIETY-S01E01/audio/L06-15 - V5091 - Kang PD - 주문 성공입니다. 파란 팀은 첫 번째 힌트를 받습니다.mp3",
      "pattern": "",
      "difficulty": "A1",
      "explanation_ref": "V5091",
      "has_explanation": true
    },
    {
      "book_code": "HS-VARIETY-S01E01",
      "book_title": "수상한 하루 — Episodio 1: El Invitado Sospechoso",
      "track_id": "V5094",
      "lesson": 7,
      "sequence": 3,
      "speaker": "Bora",
      "text": "봤죠? 드디어 본색이 나오는 거예요.",
      "translation": "¿Vieron? Por fin está mostrando su verdadera naturaleza.",
      "audio_path": "books/HS-VARIETY-S01E01/audio/L07-03 - V5094 - Bora - 봤죠 드디어 본색이 나오는 거예요.mp3",
      "pattern": "",
      "difficulty": "A1",
      "explanation_ref": "V5094",
      "has_explanation": true
    },
    {
      "book_code": "HS-VARIETY-S01E01",
      "book_title": "수상한 하루 — Episodio 1: El Invitado Sospechoso",
      "track_id": "V5095",
      "lesson": 7,
      "sequence": 4,
      "speaker": "Dami",
      "text": "아직 아무 일도 안 일어났어요. 너무 빨리 몰아가지 마세요.",
      "translation": "Todavía no ha pasado nada. No lo arrinconen tan rápido.",
      "audio_path": "books/HS-VARIETY-S01E01/audio/L07-04 - V5095 - Dami - 아직 아무 일도 안 일어났어요. 너무 빨리 몰아가지 마세요.mp3",
      "pattern": "",
      "difficulty": "A1",
      "explanation_ref": "V5095",
      "has_explanation": true
    },
    {
      "book_code": "HS-VARIETY-S01E01",
      "book_title": "수상한 하루 — Episodio 1: El Invitado Sospechoso",
      "track_id": "V5108",
      "lesson": 8,
      "sequence": 2,
      "speaker": "Taeyun",
      "text": "저는 아까 먹은 메뉴도 기억이 안 나요.",
      "translation": "Yo ni siquiera recuerdo lo que comí hace rato.",
      "audio_path": "books/HS-VARIETY-S01E01/audio/L08-02 - V5108 - Taeyun - 저는 아까 먹은 메뉴도 기억이 안 나요.mp3",
      "pattern": "",
      "difficulty": "A1",
      "explanation_ref": "V5108",
      "has_explanation": true
    },
    {
      "book_code": "HS-VARIETY-S01E01",
      "book_title": "수상한 하루 — Episodio 1: El Invitado Sospechoso",
      "track_id": "V5114",
      "lesson": 8,
      "sequence": 8,
      "speaker": "Kang PD",
      "text": "첫 번째 문제입니다. 방금 화면에 나온 과일은 무엇이었습니까?",
      "translation": "Primera pregunta. ¿Qué fruta apareció en la pantalla hace un momento?",
      "audio_path": "books/HS-VARIETY-S01E01/audio/L08-08 - V5114 - Kang PD - 첫 번째 문제입니다. 방금 화면에 나온 과일은 무엇이었습니까.mp3",
      "pattern": "",
      "difficulty": "A1",
      "explanation_ref": "V5114",
      "has_explanation": true
    },
    {
      "book_code": "HS-VARIETY-S01E01",
      "book_title": "수상한 하루 — Episodio 1: El Invitado Sospechoso",
      "track_id": "V5115",
      "lesson": 8,
      "sequence": 9,
      "speaker": "Dami",
      "text": "사과였나요? 아니면 복숭아였나요?",
      "translation": "¿Era manzana? ¿O durazno?",
      "audio_path": "books/HS-VARIETY-S01E01/audio/L08-09 - V5115 - Dami - 사과였나요 아니면 복숭아였나요.mp3",
      "pattern": "",
      "difficulty": "A1",
      "explanation_ref": "V5115",
      "has_explanation": true
    },
    {
      "book_code": "HS-VARIETY-S01E01",
      "book_title": "수상한 하루 — Episodio 1: El Invitado Sospechoso",
      "track_id": "V5117",
      "lesson": 8,
      "sequence": 11,
      "speaker": "Bora",
      "text": "왜 다미 씨가 말하기 전에 도와줘요?",
      "translation": "¿Por qué la ayuda antes de que Dami hable?",
      "audio_path": "books/HS-VARIETY-S01E01/audio/L08-11 - V5117 - Bora - 왜 다미 씨가 말하기 전에 도와줘요.mp3",
      "pattern": "",
      "difficulty": "A1",
      "explanation_ref": "V5117",
      "has_explanation": true
    },
    {
      "book_code": "HS-VARIETY-S01E01",
      "book_title": "수상한 하루 — Episodio 1: El Invitado Sospechoso",
      "track_id": "V5120",
      "lesson": 8,
      "sequence": 14,
      "speaker": "Jisoo",
      "text": "하지만 방금 답은 맞았어요. 복숭아였습니다.",
      "translation": "Pero la respuesta de hace un momento fue correcta. Era durazno.",
      "audio_path": "books/HS-VARIETY-S01E01/audio/L08-14 - V5120 - Jisoo - 하지만 방금 답은 맞았어요. 복숭아였습니다.mp3",
      "pattern": "-지만",
      "difficulty": "A1",
      "explanation_ref": "V5120",
      "has_explanation": true
    },
    {
      "book_code": "HS-VARIETY-S01E01",
      "book_title": "수상한 하루 — Episodio 1: El Invitado Sospechoso",
      "track_id": "V5121",
      "lesson": 8,
      "sequence": 15,
      "speaker": "Taeyun",
      "text": "저는 왜 틀렸는지도 모르고 틀렸어요.",
      "translation": "Yo fallé sin siquiera saber por qué fallé.",
      "audio_path": "books/HS-VARIETY-S01E01/audio/L08-15 - V5121 - Taeyun - 저는 왜 틀렸는지도 모르고 틀렸어요.mp3",
      "pattern": "",
      "difficulty": "A1",
      "explanation_ref": "V5121",
      "has_explanation": true
    },
    {
      "book_code": "HS-VARIETY-S01E01",
      "book_title": "수상한 하루 — Episodio 1: El Invitado Sospechoso",
      "track_id": "V5131",
      "lesson": 9,
      "sequence": 10,
      "speaker": "Dami",
      "text": "진짜요? 그럼 저를 계속 도와준 게 미션 때문이었어요?",
      "translation": "¿De verdad? Entonces, ¿me ayudó todo el tiempo por la misión?",
      "audio_path": "books/HS-VARIETY-S01E01/audio/L09-10 - V5131 - Dami - 진짜요 그럼 저를 계속 도와준 게 미션 때문이었어요.mp3",
      "pattern": "-았/었어요",
      "difficulty": "A1",
      "explanation_ref": "V5131",
      "has_explanation": true
    },
    {
      "book_code": "HS-VARIETY-S01E01",
      "book_title": "수상한 하루 — Episodio 1: El Invitado Sospechoso",
      "track_id": "V5140",
      "lesson": 10,
      "sequence": 4,
      "speaker": "Bora",
      "text": "잠깐만요. 그럼 진짜 미션자는 누구예요?",
      "translation": "Un momento. Entonces, ¿quién era la verdadera persona de la misión?",
      "audio_path": "books/HS-VARIETY-S01E01/audio/L10-04 - V5140 - Bora - 잠깐만요. 그럼 진짜 미션자는 누구예요.mp3",
      "pattern": "",
      "difficulty": "A1",
      "explanation_ref": "V5140",
      "has_explanation": true
    },
    {
      "book_code": "HS-VARIETY-S01E01",
      "book_title": "수상한 하루 — Episodio 1: El Invitado Sospechoso",
      "track_id": "V5141",
      "lesson": 10,
      "sequence": 5,
      "speaker": "Kang PD",
      "text": "진짜 미션자는 다미 씨였습니다.",
      "translation": "La verdadera persona con misión era Dami.",
      "audio_path": "books/HS-VARIETY-S01E01/audio/L10-05 - V5141 - Kang PD - 진짜 미션자는 다미 씨였습니다.mp3",
      "pattern": "",
      "difficulty": "A1",
      "explanation_ref": "V5141",
      "has_explanation": true
    },
    {
      "book_code": "HS-VARIETY-S01E01",
      "book_title": "수상한 하루 — Episodio 1: El Invitado Sospechoso",
      "track_id": "V5154",
      "lesson": 10,
      "sequence": 18,
      "speaker": "Minho",
      "text": "수상한 하루, 첫 번째 이야기는 여기까지입니다. 다음 주에도 의심하면서 만나요!",
      "translation": "Un Día Sospechoso, la primera historia termina aquí. ¡Nos vemos la próxima semana sospechando!",
      "audio_path": "books/HS-VARIETY-S01E01/audio/L10-18 - V5154 - Minho - 수상한 하루, 첫 번째 이야기는 여기까지입니다. 다음 주에도 의심하면서 만나요!.mp3",
      "pattern": "여기",
      "difficulty": "A1",
      "explanation_ref": "V5154",
      "has_explanation": true
    }
  ]
}
